convert_time_to_text/__init__.py
convert_time_to_text/convert_time_to_text.py
convert_time_to_text-0.3.0.dist-info/LICENSE
convert_time_to_text-0.3.0.dist-info/METADATA
convert_time_to_text-0.3.0.dist-info/WHEEL
convert_time_to_text-0.3.0.dist-info/top_level.txt
convert_time_to_text-0.3.0.dist-info/RECORD
