Metadata-Version: 2.1
Name: convert-time-to-text
Version: 0.3.0
Summary: A simple package to convert time to text.
Home-page: https://github.com/kartheekgp/convert_time_to_text
Author: Kartheek G P
Author-email: 
Classifier: Programming Language :: Python :: 3
Classifier: License :: OSI Approved :: MIT License
Classifier: Operating System :: OS Independent
Requires-Python: >=3.6
License-File: LICENSE
